{"title":"MOCAIBER, Alexandre","cargoss":["pref. Campos 2005-2009."],"author":"Luciana Pinheiro","content":"**MOCAIBER, Alexandre**\n\n\\* pref. Campos 2005-2009.\n\n***Alexandre Marcos Mocaiber Cardoso*** **nasceu em Duque de Caxias (RJ)\nno dia** 26 de janeiro de 1951.\n\nMédico, assumiu a Secretaria de Saúde do município de Campos (RJ) a\nconvite do então prefeito Arnaldo Viana (1998-2004). No pleito municipal\nrealizado em outubro de 2004 candidatou-se a vereador nessa cidade na\nlegenda do Partido Democrático Trabalhista (PDT) e foi eleito. Tomou\nposse na Câmara Municipal em janeiro de 2005 e foi escolhido presidente\nda Casa. Como tal, em abril de 2005 assumiu a prefeitura de Campos, em\ndecorrência da anulação do processo eleitoral que elegera Carlos Alberto\nCampista, do PDT.\n\nNa nova eleição municipal convocada para março de 2006, concorreu à\nprefeitura na legenda do Partido Socialista Brasileiro (PSB) e foi\neleito no segundo turno, derrotando Geraldo Pudim, candidato do Partido\ndo Movimento Democrático Brasileiro (PMDB) apoiado por Rosinha e Anthony\nGarotinho. No decorrer de março de 2008 foi afastado do cargo de\nprefeito a pedido do Ministério Público Federal, por suspeita de\nenvolvimento em um esquema de superfaturamento de contratos do município\ndesmantelado pela operação Telhado de Vidro, empreendida pela Polícia\nFederal, que constatou a falta de controle nas contratações realizadas\npela prefeitura. Na ocasião foi substituído pelo vice-prefeito Roberto\nHenriques, do PMDB. No mês seguinte, contudo, reassumiu a prefeitura por\ndecisão do Supremo Tribunal de Justiça (STJ), que considerou seu\nafastamento inconstitucional. Permaneceu à frente do município até 1^o^\nde janeiro de 2009, quando transferiu o cargo para Rosinha Garotinho,\neleita pelo PMDB.\n\nEm agosto de 2010 teve seu pedido de candidatura a deputado estadual\nindeferido pelo Tribunal Regional Eleitoral do Rio de Janeiro (TRE-RJ),\nsob a alegação de contas rejeitadas pelo Tribunal de Contas do Estado\n(TCE-RJ) e de inelegibilidade decretada por abuso de poder econômico.\n\nCasou-se com Cristina Mocaiber, com quem teve três filhos.\n\nFoi coautor de *Programa de Saúde Mental*, publicado em 1997.\n\n*Luciana Pinheiro*\n\nFONTES: Blog Vitor Longo. Disponível em:\n\\<http://blogvitorlongo.blogspot.com/\\>. Acesso em: 16/3/2011; CÂM. VER.\nCAMPOS DOS GOYTACAZES. Disponível em: \\<www.camaracampos.rj.gov.br/\\>.\nAcesso em: 15/3/2011; DivulgaCand2010–TSE. Disponível em:\n\\<http://divulgacand2010.tse.jus.br/divulgacand2010/jsp/abrirTelaDetalheCandidato.action?sqCand=190000000730&sgUe=RJ\\>.\nAcesso em: 15/3/2010; *Folha de S.Paulo*. Disponível em:\n\\<www1.folha.uol.com.br/folha/brasil/ult96u406666.shtml\\>. Acesso em:\n16/3/2011; G1. Disponível em: \\<http://g1.globo.com/\\>. Acesso em:\n15/3/2011; *Globo*. Disponível em: \\<http://oglobo.globo.com/\\>. Acesso\nem: 16/3/2011; Terra Notícias. Disponível em:\n\\<http://noticias.terra.com.br/eleicoes/2010/noticias/0,,OI4602057-EI15336,00-RJ+Exprefeito+de+Campos+dos+Goytacazes+e+impugnado+pelo+TRE.html\\>.\nAcesso em: 15/3/2011; TRIB. SUP. ELEIT. Disponível em:\n\\<www.tse.gov.br/\\>. Acesso em: 15/3/2011.\n","ref":"FONTES: Blog Vitor Longo. Disponível em:\n\\<http://blogvitorlongo.blogspot.com/\\>. Acesso em: 16/3/2011; CÂM. VER.\nCAMPOS DOS GOYTACAZES. Disponível em: \\<www.camaracampos.rj.gov.br/\\>.\nAcesso em: 15/3/2011; DivulgaCand2010–TSE. Disponível em:\n\\<http://divulgacand2010.tse.jus.br/divulgacand2010/jsp/abrirTelaDetalheCandidato.action?sqCand=190000000730&sgUe=RJ\\>.\nAcesso em: 15/3/2010; *Folha de S.Paulo*. Disponível em:\n\\<www1.folha.uol.com.br/folha/brasil/ult96u406666.shtml\\>. Acesso em:\n16/3/2011; G1. Disponível em: \\<http://g1.globo.com/\\>. Acesso em:\n15/3/2011; *Globo*. Disponível em: \\<http://oglobo.globo.com/\\>. Acesso\nem: 16/3/2011; Terra Notícias. Disponível em:\n\\<http://noticias.terra.com.br/eleicoes/2010/noticias/0,,OI4602057-EI15336,00-RJ+Exprefeito+de+Campos+dos+Goytacazes+e+impugnado+pelo+TRE.html\\>.\nAcesso em: 15/3/2011; TRIB. SUP. ELEIT. Disponível em:\n\\<www.tse.gov.br/\\>. Acesso em: 15/3/2011.\n","dic":"DPRRJ"}