{"title":"MONASSA, Helvécio Abdalla","cargoss":["Deputado Estadual"],"cargos_esp":[0],"datas_ini":[1967],"datas_fim":[1969],"estados":["RJ"],"autor":["Nayara Emerick Lamb"],"content":"**MONASSA, Helvécio Abdalla**\n\n\\* dep. est. RJ 1967-1969.\n\n*Helvécio Abdalla Monassa* graduou-se em direito.\n\nEm 1932 foi contador da Superintendência do Ensino Comercial, órgão\nsubordinado ao ministro da Educação e Saúde Pública, que tinha a função\nde fiscalizar os estabelecimentos de ensino comercial. Advogou no Rio de\nJaneiro na década de 1930. Em setembro de 1935, junto com outros\nadvogados, inclusive Antônio Dias Tavares Bastos, representante do\nPartido Socialista Brasileiro, enviou ao Supremo Tribunal Federal (STF)\numa petição em favor da concessão de *habeas corpus* a Genny Gleiser,\njovem judia de origem romena, presa durante o governo do presidente\nGetúlio Vargas (1930-1945), acusada de ligações com o comunismo.\n\nCandidatou-se a deputado estadual no Rio de Janeiro, em janeiro de 1947,\nna legenda do partido Esquerda Democrática (ED), mas não se elegeu.\n\nElegeu-se vereador em Niterói (RJ), tendo presidido a Câmara Municipal nos anos de 1952, 1954, 1957 e 1958.\n===========================================================================================================\n\nEm outubro de 1965 o regime militar, iniciado no ano anterior, editou o\nAto Institucional n^o^ 2, que extinguiu os partidos políticos em vigor\naté então. Em novembro foi expedido o Ato Complementar n^o^ 4, que\ndispôs sobre a reorganização partidária, que resultou no bipartidarismo.\nDois partidos foram criados: a Aliança Renovadora Nacional (Arena), de\napoio ao regime iniciado em 1964, e o Movimento Democrático Brasileiro\n(MDB), de oposição. No pleito seguinte, realizado em 15 de novembro de\n1966, Helvécio Monassa se elegeu deputado estadual no Rio de Janeiro, na\nlegenda do Movimento Democrático Brasileiro (MDB) e assumiu o mandato na\nAssembleia Legislativa do Estado do Rio de Janeiro (ALERJ) no ano\nseguinte.\n\nHelvécio Monassa não exerceu o mandato até o fim da legislatura. Foi\ncassado e teve seus direitos políticos suspensos por dez anos pelo\nConselho de Segurança Nacional, com base no Ato Institucional n^o^ 5, no\ndia 13 de março de 1969.\n\nDurante sua trajetória foi, ainda, professor do Departamento Nacional de\nEducação e chefe do setor de limpeza e construção das praças da Região\nOceânica de Niterói, da Empresa Municipal de Moradia, Urbanização e\nSaneamento (Emusa).\n\nFaleceu em 2007.\n\n*Nayara Emerick Lamb*\n\nFONTES: CÂM. MUN. NITERÓI. Arquivo Divaldo Aguiar Lopes. Disponível em:\n\\<http://camaraniteroi.rj.gov.br/2010/12/20/helvecio-abdala-monassa\\>.\nAcesso em: 29/5/2011; CARDIANO, F. *Eleições*; *Diário Oficial da\nUnião*. Disponível em:\n\\<www.jusbrasil.com.br/diarios/2352492/dou-secao-1-28-05-1945-pg-27\\>.\nAcesso em: 29/5/2011;\n\\<www.jusbrasil.com.br/diarios/2436362/dou-secao-1-31-08-1943-pg-9\\>.\nAcesso em: 29/5/2011;\n\\<www.jusbrasil.com.br/diarios/2006117/dou-secao-1-15-03-1932-pg-4/pdfView\\>.\nAcesso em: 29/5/2011; *Diário Oficial da União* (15/3/1932, p. 13-14);\nFERREIRA, J. *Sociedade*; GODOY, A. *Direito*; *Jornal do Brasil*\n(14/3/1969, p. 3). PREF. MUN. NITERÓI. Disponível em:\n\\<www.niteroi.rj.gov.br/downloads/do/2007/07\\_Jul/06.pdf\\>. Acesso em:\n29/5/2011; ROLLEMBERG, D. *Ditadura*; TOLEDO, C. *Governo*.\n","ref":"FONTES: CÂM. MUN. NITERÓI. Arquivo Divaldo Aguiar Lopes. Disponível em:\n\\<http://camaraniteroi.rj.gov.br/2010/12/20/helvecio-abdala-monassa\\>.\nAcesso em: 29/5/2011; CARDIANO, F. *Eleições*; *Diário Oficial da\nUnião*. Disponível em:\n\\<www.jusbrasil.com.br/diarios/2352492/dou-secao-1-28-05-1945-pg-27\\>.\nAcesso em: 29/5/2011;\n\\<www.jusbrasil.com.br/diarios/2436362/dou-secao-1-31-08-1943-pg-9\\>.\nAcesso em: 29/5/2011;\n\\<www.jusbrasil.com.br/diarios/2006117/dou-secao-1-15-03-1932-pg-4/pdfView\\>.\nAcesso em: 29/5/2011; *Diário Oficial da União* (15/3/1932, p. 13-14);\nFERREIRA, J. *Sociedade*; GODOY, A. *Direito*; *Jornal do Brasil*\n(14/3/1969, p. 3). PREF. MUN. NITERÓI. Disponível em:\n\\<www.niteroi.rj.gov.br/downloads/do/2007/07\\_Jul/06.pdf\\>. Acesso em:\n29/5/2011; ROLLEMBERG, D. *Ditadura*; TOLEDO, C. *Governo*.\n","dic":"DPRRJ"}
